wedata/__init__.py
wedata/common/__init__.py
wedata/common/base_table_client/__init__.py
wedata/common/base_table_client/base.py
wedata/common/cloud_sdk_client/__init__.py
wedata/common/cloud_sdk_client/client.py
wedata/common/cloud_sdk_client/models.py
wedata/common/cloud_sdk_client/utils.py
wedata/common/constants/__init__.py
wedata/common/constants/constants.py
wedata/common/constants/engine_types.py
wedata/common/entities/__init__.py
wedata/common/entities/column_info.py
wedata/common/entities/environment_variables.py
wedata/common/entities/feature.py
wedata/common/entities/feature_column_info.py
wedata/common/entities/feature_function.py
wedata/common/entities/feature_lookup.py
wedata/common/entities/feature_spec.py
wedata/common/entities/feature_spec_constants.py
wedata/common/entities/feature_table.py
wedata/common/entities/feature_table_info.py
wedata/common/entities/function_info.py
wedata/common/entities/on_demand_column_info.py
wedata/common/entities/source_data_column_info.py
wedata/common/entities/training_set.py
wedata/common/feast_client/__init__.py
wedata/common/feast_client/feast_client.py
wedata/common/log/__init__.py
wedata/common/log/logger.py
wedata/common/protos/__init__.py
wedata/common/protos/feature_store_pb2.py
wedata/common/spark_client/__init__.py
wedata/common/spark_client/spark_client.py
wedata/common/utils/__init__.py
wedata/common/utils/common_utils.py
wedata/common/utils/env_utils.py
wedata/common/utils/feature_lookup_utils.py
wedata/common/utils/feature_spec_utils.py
wedata/common/utils/feature_utils.py
wedata/common/utils/on_demand_utils.py
wedata/common/utils/schema_utils.py
wedata/common/utils/signature_utils.py
wedata/common/utils/topological_sort.py
wedata/common/utils/training_set_utils.py
wedata/common/utils/uc_utils.py
wedata/common/utils/validation_utils.py
wedata/feature_engineering/__init__.py
wedata/feature_engineering/client.py
wedata/feature_engineering/mlflow_model.py
tencent_wedata_feature_engineering_dev-0.6.3.dist-info/METADATA
tencent_wedata_feature_engineering_dev-0.6.3.dist-info/WHEEL
tencent_wedata_feature_engineering_dev-0.6.3.dist-info/top_level.txt
tencent_wedata_feature_engineering_dev-0.6.3.dist-info/RECORD
